treeswift/Node.py
treeswift/Tree.py
treeswift/__init__.py
treeswift-1.1.45.dist-info/LICENSE
treeswift-1.1.45.dist-info/METADATA
treeswift-1.1.45.dist-info/WHEEL
treeswift-1.1.45.dist-info/top_level.txt
treeswift-1.1.45.dist-info/RECORD
