Metadata-Version: 2.1
Name: treeswift
Version: 1.1.45
Summary: TreeSwift: Fast tree module for Python 2 and 3
Home-page: https://github.com/niemasd/TreeSwift
Author: Niema Moshiri
Author-email: niemamoshiri@gmail.com
Project-URL: Bug Reports, https://github.com/niemasd/TreeSwift/issues
Project-URL: Source, https://github.com/niemasd/TreeSwift
Keywords: tree phylogenetics fast
Classifier: Development Status :: 3 - Alpha
Classifier: Intended Audience :: Developers
Classifier: Topic :: Software Development :: Build Tools
Classifier: License :: OSI Approved :: GNU General Public License v3 or later (GPLv3+)
Classifier: Programming Language :: Python :: 3
Classifier: Programming Language :: Python :: 3.7
Classifier: Programming Language :: Python :: 3.8
Classifier: Programming Language :: Python :: 3.9
Classifier: Programming Language :: Python :: 3.10
Classifier: Programming Language :: Python :: 3.11
License-File: LICENSE
Provides-Extra: dev
Requires-Dist: check-manifest ; extra == 'dev'
